transformer/__init__.py
transformer/data_feeder.py
transformer/dataset.py
transformer/losses.py
transformer/metrics.py
transformer/model_runner.py
transformer/predict.py
transformer/predictor.py
transformer/train.py
transformer/model/__init__.py
transformer/model/decoder.py
transformer/model/decoder_layer.py
transformer/model/encoder.py
transformer/model/encoder_layer.py
transformer/model/masking.py
transformer/model/multi_head_attention.py
transformer/model/position_wise_feed_forward.py
transformer/model/positional_encoding.py
transformer/model/scaled_dot_product_attention.py
transformer/model/state.py
transformer/model/sublayers.py
transformer/model/transformer.py
transformer_pytorch-0.0.1.dist-info/LICENSE
transformer_pytorch-0.0.1.dist-info/METADATA
transformer_pytorch-0.0.1.dist-info/WHEEL
transformer_pytorch-0.0.1.dist-info/top_level.txt
transformer_pytorch-0.0.1.dist-info/RECORD
