Metadata-Version: 2.1
Name: transformer-pytorch
Version: 0.0.1
Summary: PyTorch implementation of Transformer from "Attention is All You Need".
Home-page: https://github.com/dreamgonfly/transformer-pytorch
Author: Yongrae Jo
Author-email: dreamgonfly@gmail.com
License: MIT
Keywords: transformer pytorch translation
Platform: UNKNOWN
Classifier: Development Status :: 4 - Beta
Classifier: Topic :: Utilities
Classifier: Programming Language :: Python :: 3
Classifier: Programming Language :: Python :: 3.6
Classifier: Programming Language :: Python :: 3.7
Classifier: Programming Language :: Python :: 3.8
Classifier: License :: OSI Approved :: MIT License
Requires-Python: >=3.7
